rtb_toolbox/README.md
rtb_toolbox/__init__.py
rtb_toolbox/forward_dynamics/__init__.py
rtb_toolbox/forward_kinematics/__init__.py
rtb_toolbox/frame/__init__.py
rtb_toolbox/images/full_ik.png
rtb_toolbox/images/partial_ik.png
rtb_toolbox/images/tau1.png
rtb_toolbox/images/tau2.png
rtb_toolbox/images/trajectories.png
rtb_toolbox/inverse_kinematics/__init__.py
rtb_toolbox/link/__init__.py
rtb_toolbox/robots/SCARA.py
rtb_toolbox/robots/comau.py
rtb_toolbox/robots/puma260.py
rtb_toolbox/robots/ur3.py
rtb_toolbox/symbols.py
rtb_toolbox/trajectory/__init__.py
rtb_toolbox/utils/__init__.py
rtb_toolbox-0.1.67.dist-info/METADATA
rtb_toolbox-0.1.67.dist-info/WHEEL
rtb_toolbox-0.1.67.dist-info/RECORD
