Metadata-Version: 2.1
Name: rtb-toolbox
Version: 0.1.67
Summary: 
Author: Miguel
Author-email: miguellukas52@gmail.com
Requires-Python: >=3.10,<4.0
Classifier: Programming Language :: Python :: 3
Classifier: Programming Language :: Python :: 3.10
Classifier: Programming Language :: Python :: 3.11
Classifier: Programming Language :: Python :: 3.12
Requires-Dist: numpy (>=1.26.2,<2.0.0)
Requires-Dist: pymoo (>=0.6.1.1,<0.7.0.0)
Requires-Dist: sympy (>=1.12,<2.0)
